MANIFEST.in
README.rst
setup.cfg
setup.py
tests/__init__.py
tests/base.py
tests/test_crud_filtered.py
tests/test_crud_html.py
tests/test_rest_json.py
tests/test_rest_json_body.py
tests/test_rest_json_dictified.py
tgext/__init__.py
tgext.crud.egg-info/PKG-INFO
tgext.crud.egg-info/SOURCES.txt
tgext.crud.egg-info/dependency_links.txt
tgext.crud.egg-info/entry_points.txt
tgext.crud.egg-info/namespace_packages.txt
tgext.crud.egg-info/pbr.json
tgext.crud.egg-info/requires.txt
tgext.crud.egg-info/top_level.txt
tgext.crud.egg-info/zip-safe
tgext/crud/__init__.py
tgext/crud/_compat.py
tgext/crud/controller.py
tgext/crud/decorators.py
tgext/crud/resources.py
tgext/crud/utils.py
tgext/crud/validators.py
tgext/crud/templates/__init__.py
tgext/crud/templates/edit.html
tgext/crud/templates/edit.jinja
tgext/crud/templates/edit.mak
tgext/crud/templates/edit.xhtml
tgext/crud/templates/get_all.html
tgext/crud/templates/get_all.jinja
tgext/crud/templates/get_all.mak
tgext/crud/templates/get_all.xhtml
tgext/crud/templates/get_delete.html
tgext/crud/templates/get_delete.jinja
tgext/crud/templates/get_one.html
tgext/crud/templates/get_one.jinja
tgext/crud/templates/get_one.mak
tgext/crud/templates/get_one.xhtml
tgext/crud/templates/menu_items.mak
tgext/crud/templates/new.html
tgext/crud/templates/new.jinja
tgext/crud/templates/new.mak
tgext/crud/templates/new.xhtml